treemodeladmin/__init__.py
treemodeladmin/apps.py
treemodeladmin/helpers.py
treemodeladmin/options.py
treemodeladmin/views.py
treemodeladmin/static/treemodeladmin/css/index.css
treemodeladmin/templates/treemodeladmin/index.html
treemodeladmin/templates/treemodeladmin/includes/breadcrumb.html
treemodeladmin/templates/treemodeladmin/includes/tree_result_list.html
treemodeladmin/templates/treemodeladmin/includes/tree_result_row.html
treemodeladmin/templatetags/__init__.py
treemodeladmin/templatetags/treemodeladmin_tags.py
treemodeladmin/tests/__init__.py
treemodeladmin/tests/settings.py
treemodeladmin/tests/test_options.py
treemodeladmin/tests/test_views.py
treemodeladmin/tests/urls.py
treemodeladmin/tests/treemodeladmintest/__init__.py
treemodeladmin/tests/treemodeladmintest/apps.py
treemodeladmin/tests/treemodeladmintest/models.py
treemodeladmin/tests/treemodeladmintest/wagtail_hooks.py
treemodeladmin/tests/treemodeladmintest/migrations/0001_initial.py
treemodeladmin/tests/treemodeladmintest/migrations/__init__.py
wagtail_treemodeladmin-1.9.2.dist-info/LICENSE
wagtail_treemodeladmin-1.9.2.dist-info/METADATA
wagtail_treemodeladmin-1.9.2.dist-info/WHEEL
wagtail_treemodeladmin-1.9.2.dist-info/top_level.txt
wagtail_treemodeladmin-1.9.2.dist-info/RECORD
