Metadata-Version: 2.1
Name: wagtail-treemodeladmin
Version: 1.9.2
Summary: TreeModelAdmin for Wagtail
Author-email: CFPB <tech@cfpb.gov>
License: CC0
Project-URL: Homepage, https://github.com/cfpb/wagtail-treemodeladmin
Project-URL: Bug Reports, https://github.com/cfpb/wagtail-treemodeladmin/issues
Project-URL: Source, https://github.com/cfpb/wagtail-treemodeladmin
Classifier: Framework :: Django
Classifier: Framework :: Django :: 3.2
Classifier: Framework :: Django :: 4.2
Classifier: Framework :: Wagtail
Classifier: Framework :: Wagtail :: 4
Classifier: Framework :: Wagtail :: 5
Classifier: License :: CC0 1.0 Universal (CC0 1.0) Public Domain Dedication
Classifier: License :: Public Domain
Classifier: Programming Language :: Python
Classifier: Programming Language :: Python :: 3
Requires-Python: >=3.8
License-File: LICENSE
Requires-Dist: wagtail >=5.1
Requires-Dist: wagtail-modeladmin >=1.0
Provides-Extra: testing
Requires-Dist: coverage[toml] ; extra == 'testing'
